{
  "resourceType": "DeviceDefinition",
  "id": "example-devicemodel-interbody-fusion-system",
  "meta": {
    "profile": [
      "http://hl7.org/fhir/uv/order-catalog/StructureDefinition/DeviceModel"
    ]
  },
  "language": "en-US",
  "extension": [
    {
      "url": "http://hl7.org/fhir/uv/order-catalog/StructureDefinition/CatalogReference",
      "valueReference": {
        "reference": "Composition/example-device-catalog-header"
      }
    }
  ],
  "identifier": [
    {
      "use": "secondary",
      "type": {
        "coding": [
          {
            "code": "UDI",
            "system": "http://terminology.hl7.org/CodeSystem/v2-0203",
            "display": "Universal Device Identifier"
          }
        ]
      },
      "system": "http://hl7.org/fhir/NamingSystem/gs1-di",
      "value": "00843210101415"
    }
  ],
  "udiDeviceIdentifier": [
    {
      "deviceIdentifier": "B417F12260121",
      "issuer": "http://hl7.org/fhir/NamingSystem/hibcc-diI",
      "jurisdiction": "http://hl7.org/fhir/NamingSystem/us-fda-udi",
      "marketDistribution": [
        {
          "marketPeriod": {
            "start": "2017-08-22"
          },
          "subJurisdiction": "http://hl7.org/fhir/NamingSystem/us-fda-udi"
        }
      ]
    }
  ],
  "manufacturerString": "Altus Spine, LLC",
  "deviceName": [
    {
      "name": "Imola Interbody Fusion System",
      "type": "registered-name"
    }
  ],
  "modelNumber": "F12260-12",
  "classification": [
    {
      "type": {
        "coding": [
          {
            "code": "60762",
            "system": "http://terminology.hl7.org/CodeSystem/GMDN",
            "display": "Polymeric spinal interbody fusion cage"
          }
        ]
      }
    },
    {
      "type": {
        "coding": [
          {
            "code": "257275005",
            "system": "http://snomed.info/sct",
            "display": "Spinal cage"
          }
        ]
      }
    },
    {
      "type": {
        "coding": [
          {
            "code": "P090701",
            "system": "urn:oid:1.2.250.1.213.2.68",
            "display": "Spinal fusion systems"
          }
        ]
      }
    }
  ],
  "safety": [
    {
      "coding": [
        {
          "code": "C113844",
          "system": "urn:oid:2.16.840.1.113883.3.26.1.1",
          "display": "Labeling does not Contain MRI Safety Information"
        }
      ]
    }
  ],
  "languageCode": [
    {
      "coding": [
        {
          "code": "en-US",
          "system": "http://terminology.hl7.org/CodeSystem/iso639-1",
          "display": "American English"
        }
      ]
    }
  ],
  "property": [
    {
      "type": {
        "text": "For single use"
      },
      "valueBoolean": true
    },
    {
      "type": {
        "text": "Prescription use"
      },
      "valueBoolean": true
    },
    {
      "type": {
        "text": "Over the counter"
      },
      "valueBoolean": false
    },
    {
      "type": {
        "text": "Human Cell, Tissue or Cellular or Tissue-Based Product (HCT/P)"
      },
      "valueBoolean": false
    }
  ],
  "contact": [
    {
      "system": "email",
      "value": "Info@altus-spine.com"
    }
  ],
  "guideline": {
    "relatedArtifact": [
      {
        "type": "documentation",
        "label": "Device described in GUDID:",
        "document": {
          "url": "https://accessgudid.nlm.nih.gov/devices/B417F12260121"
        }
      }
    ]
  }
}
