<?xml version="1.0" encoding="UTF-8"?>
<SpecimenDefinition xmlns="http://hl7.org/fhir"
    xmlns:xsi="http://www.w3.org/2001/XMLSchema-instance"
    xsi:schemaLocation="http://hl7.org/fhir http://hl7.org/fhir/specimendefinition.xsd">
    <id value="example-specimen-2ml-serum"/>
    <meta>
        <profile
            value="http://hl7.org/fhir/uv/order-catalog/StructureDefinition/LabSpecimenDefinition"/>
    </meta>
    <language value="en-US"/>
	<url value="http://hl7.org/fhir/uv/order-catalog/SpecimenDefinition/example-specimen-2ml-serum"/>
	<status value="active"/>
    <typeCollected>
        <coding>
            <system value="http://snomed.info/sct"/>
            <code value="122555007"/>
            <display value="Venous blood specimen (specimen)"/>
        </coding>
    </typeCollected>
    <typeTested>
        <type>
            <coding>
                <system value="http://terminology.hl7.org/CodeSystem/v2-0487"/>
                <code value="SER"/>
                <display value="Serum"/>
            </coding>
        </type>
        <preference value="preferred"/>
        <container>
            <capacity>
                <value value="5"/>
                <unit value="milliliter"/>
                <system value="http://unitsofmeasure.org"/>
                <code value="mL"/>
            </capacity>
            <minimumVolumeQuantity>
                <value value="2"/>
                <system value="http://unitsofmeasure.org"/>
                <code value="mL"/>
            </minimumVolumeQuantity>
        </container>
        <retentionTime>
            <value value="24"/>
            <unit value="hour"/>
            <system value="http://unitsofmeasure.org"/>
            <code value="h"/>
        </retentionTime>
        <rejectionCriterion>
            <coding>
                <system value="http://terminology.hl7.org/CodeSystem/rejection-criteria"/>
                <code value="hemolized"/>
            </coding>
            <text value="blood specimen hemolized"/>
        </rejectionCriterion>
        <handling>
            <temperatureQualifier>
                <text value="room temperature or refrigerated"/>
            </temperatureQualifier>
            <maxDuration>
                <value value="4"/>
                <unit value="day"/>
                <system value="http://unitsofmeasure.org"/>
                <code value="d"/>
            </maxDuration>
        </handling>
    </typeTested>
</SpecimenDefinition>
